richparser/__init__.py
richparser/parser.py
richparser-1.0.1.dist-info/METADATA
richparser-1.0.1.dist-info/WHEEL
richparser-1.0.1.dist-info/licenses/LICENSE
richparser-1.0.1.dist-info/RECORD
